pepys_import/__init__.py
pepys_import/core/__init__.py
pepys_import/core/formats/__init__.py
pepys_import/core/formats/file_data.py
pepys_import/core/formats/location.py
pepys_import/core/formats/repl_file.py
pepys_import/core/formats/state.py
pepys_import/core/formats/state2.py
pepys_import/core/formats/unit_conversion.py
pepys_import/core/store/__init__.py
pepys_import/core/store/data_store.py
pepys_import/core/store/db_base.py
pepys_import/core/store/db_status.py
pepys_import/core/store/postgres_db.py
pepys_import/core/store/sqlite_db.py
pepys_import/core/store/table_summary.py
pepys_import/core/store/uuid.py
pepys_import/database/__init__.py
pepys_import/file/__init__.py
pepys_import/file/core_parser.py
pepys_import/file/file_processor.py
pepys_import/file/nmea_parser.py
pepys_import/file/replay_parser.py
pepys_import/resolvers/__init__.py
pepys_import/resolvers/command_line_input.py
pepys_import/resolvers/command_line_resolver.py
pepys_import/resolvers/data_resolver.py
pepys_import/resolvers/default_resolver.py
pepys_import/utils/__init__.py
pepys_import/utils/branding_util.py
pepys_import/utils/data_store_utils.py
pepys_import/utils/geoalchemy_utils.py
pepys_import-0.0.4.dist-info/LICENSE
pepys_import-0.0.4.dist-info/METADATA
pepys_import-0.0.4.dist-info/WHEEL
pepys_import-0.0.4.dist-info/top_level.txt
pepys_import-0.0.4.dist-info/RECORD
