Metadata-Version: 2.1
Name: pepys-import
Version: 0.0.4
Summary: Python library to handle database ingest of geospatial track (and other) data 
Home-page: https://github.com/debrief/pepys-import
Author: Ian Mayo
Author-email: ian@planetmayo.com
License: Apache Software License 2.0
Keywords: pepys_import
Platform: UNKNOWN
Classifier: Development Status :: 2 - Pre-Alpha
Classifier: Intended Audience :: Developers
Classifier: License :: OSI Approved :: Apache Software License
Classifier: Natural Language :: English
Classifier: Programming Language :: Python :: 2
Classifier: Programming Language :: Python :: 2.7
Classifier: Programming Language :: Python :: 3
Classifier: Programming Language :: Python :: 3.5
Classifier: Programming Language :: Python :: 3.6
Classifier: Programming Language :: Python :: 3.7
Classifier: Programming Language :: Python :: 3.8
Requires-Python: >=2.7, !=3.0.*, !=3.1.*, !=3.2.*, !=3.3.*, !=3.4.*
